seperno/__init__.py
seperno/linux/seperno.so
seperno-1.4.4.dist-info/METADATA
seperno-1.4.4.dist-info/WHEEL
seperno-1.4.4.dist-info/top_level.txt
seperno-1.4.4.dist-info/RECORD
